xailib/__init__.py
xailib/xailib_base.py
xailib/xailib_image.py
xailib/xailib_tabular.py
xailib/xailib_text.py
xailib/xailib_transparent_by_design.py
xailib/xailib_ts.py
xailib/data_loaders/__init__.py
xailib/data_loaders/dataframe_loader.py
xailib/explainers/__init__.py
xailib/explainers/abele_explainer.py
xailib/explainers/gradcam_explainer.py
xailib/explainers/intgrad_explainer.py
xailib/explainers/lasts_explainer.py
xailib/explainers/lime_explainer.py
xailib/explainers/lore_explainer.py
xailib/explainers/nam_explainer_tab.py
xailib/explainers/rise_explainer.py
xailib/explainers/shap_explainer_tab.py
xailib/metrics/__init__.py
xailib/metrics/insertiondeletion.py
xailib/models/__init__.py
xailib/models/bbox.py
xailib/models/keras_classifier_wrapper.py
xailib/models/keras_ts_classifier_wrapper.py
xailib/models/sklearn_classifier_wrapper.py
xailib/models/sklearn_ts_classifier_wrapper.py
XAI_Library-0.0.4.dist-info/LICENSE.txt
XAI_Library-0.0.4.dist-info/METADATA
XAI_Library-0.0.4.dist-info/WHEEL
XAI_Library-0.0.4.dist-info/top_level.txt
XAI_Library-0.0.4.dist-info/RECORD
